// class version 61.0 (61)
// access flags 0x4021
// signature Ljava/lang/Enum<Lunchanged/ExampleEnum;>;
// declaration: unchanged/ExampleEnum extends java.lang.Enum<unchanged.ExampleEnum>
public enum unchanged/ExampleEnum extends java/lang/Enum {

  // compiled from: ExampleEnum.java
  NESTMEMBER unchanged/ExampleEnum$1
  PERMITTEDSUBCLASS unchanged/ExampleEnum$1
  // access flags 0x4010
  final enum INNERCLASS unchanged/ExampleEnum$1 null null

  // access flags 0x4019
  public final static enum Lunchanged/ExampleEnum; A

  // access flags 0x4019
  public final static enum Lunchanged/ExampleEnum; B

  // access flags 0x12
  private final I value

  // access flags 0x101A
  private final static synthetic [Lunchanged/ExampleEnum; $VALUES

  // access flags 0x9
  public static values()[Lunchanged/ExampleEnum;
   L0
    LINENUMBER 3 L0
    GETSTATIC unchanged/ExampleEnum.$VALUES : [Lunchanged/ExampleEnum;
    INVOKEVIRTUAL [Lunchanged/ExampleEnum;.clone ()Ljava/lang/Object;
    CHECKCAST [Lunchanged/ExampleEnum;
    ARETURN
    MAXSTACK = 1
    MAXLOCALS = 0

  // access flags 0x9
  public static valueOf(Ljava/lang/String;)Lunchanged/ExampleEnum;
   L0
    LINENUMBER 3 L0
    LDC Lunchanged/ExampleEnum;.class
    ALOAD 0
    INVOKESTATIC java/lang/Enum.valueOf (Ljava/lang/Class;Ljava/lang/String;)Ljava/lang/Enum;
    CHECKCAST unchanged/ExampleEnum
    ARETURN
   L1
    LOCALVARIABLE name Ljava/lang/String; L0 L1 0
    MAXSTACK = 2
    MAXLOCALS = 1

  // access flags 0x2
  // signature (I)V
  // declaration: void <init>(int)
  private <init>(Ljava/lang/String;II)V
   L0
    LINENUMBER 12 L0
    ALOAD 0
    ALOAD 1
    ILOAD 2
    INVOKESPECIAL java/lang/Enum.<init> (Ljava/lang/String;I)V
   L1
    LINENUMBER 13 L1
    ALOAD 0
    ILOAD 3
    PUTFIELD unchanged/ExampleEnum.value : I
   L2
    LINENUMBER 14 L2
    RETURN
   L3
    LOCALVARIABLE this Lunchanged/ExampleEnum; L0 L3 0
    LOCALVARIABLE value I L0 L3 3
    MAXSTACK = 3
    MAXLOCALS = 4

  // access flags 0x100A
  private static synthetic $values()[Lunchanged/ExampleEnum;
   L0
    LINENUMBER 3 L0
    ICONST_2
    ANEWARRAY unchanged/ExampleEnum
    DUP
    ICONST_0
    GETSTATIC unchanged/ExampleEnum.A : Lunchanged/ExampleEnum;
    AASTORE
    DUP
    ICONST_1
    GETSTATIC unchanged/ExampleEnum.B : Lunchanged/ExampleEnum;
    AASTORE
    ARETURN
    MAXSTACK = 4
    MAXLOCALS = 0

  // access flags 0x8
  static <clinit>()V
   L0
    LINENUMBER 4 L0
    NEW unchanged/ExampleEnum
    DUP
    LDC "A"
    ICONST_0
    ICONST_1
    INVOKESPECIAL unchanged/ExampleEnum.<init> (Ljava/lang/String;II)V
    PUTSTATIC unchanged/ExampleEnum.A : Lunchanged/ExampleEnum;
    NEW unchanged/ExampleEnum$1
    DUP
    LDC "B"
    ICONST_1
    ICONST_2
    INVOKESPECIAL unchanged/ExampleEnum$1.<init> (Ljava/lang/String;II)V
    PUTSTATIC unchanged/ExampleEnum.B : Lunchanged/ExampleEnum;
   L1
    LINENUMBER 3 L1
    INVOKESTATIC unchanged/ExampleEnum.$values ()[Lunchanged/ExampleEnum;
    PUTSTATIC unchanged/ExampleEnum.$VALUES : [Lunchanged/ExampleEnum;
    RETURN
    MAXSTACK = 5
    MAXLOCALS = 0
}
