// class version 61.0 (61)
// access flags 0x421
public abstract class other/ExampleClass {

  // compiled from: ExampleClass.java

  @Lother/ExampleAnnotation;(value="Hi", list={"First", "Second", "Third"}, nested=@Lother/SimpleAnnotation;(value="Inner"))
  NESTMEMBER other/ExampleClass$ExampleRecord
  // access flags 0x19
  public final static INNERCLASS other/ExampleClass$ExampleRecord other/ExampleClass ExampleRecord
  // access flags 0x19
  public final static INNERCLASS java/lang/invoke/MethodHandles$Lookup java/lang/invoke/MethodHandles Lookup

  // access flags 0x1
  public F publicField

  // access flags 0x11
  public final I publicFinalField = 1

  // access flags 0x12
  private final Z annotatedPrivateFinalField = 1
  @Lother/SimpleAnnotation;(value="This is a Field") // invisible

  // access flags 0x9
  public static D publicStaticField

  // access flags 0x19
  public final static C PUBLIC_STATIC_FINAL_FIELD = 120

  // access flags 0x1
  public <init>()V
   L0
    LINENUMBER 7 L0
    ALOAD 0
    INVOKESPECIAL java/lang/Object.<init> ()V
   L1
    LINENUMBER 8 L1
    ALOAD 0
    LDC 2.5
    PUTFIELD other/ExampleClass.publicField : F
   L2
    LINENUMBER 9 L2
    ALOAD 0
    ICONST_1
    PUTFIELD other/ExampleClass.publicFinalField : I
   L3
    LINENUMBER 11 L3
    ALOAD 0
    ICONST_1
    PUTFIELD other/ExampleClass.annotatedPrivateFinalField : Z
    RETURN
   L4
    LOCALVARIABLE this Lother/ExampleClass; L0 L4 0
    MAXSTACK = 2
    MAXLOCALS = 1

  // access flags 0x1
  public instanceMethod()V
   L0
    LINENUMBER 18 L0
    ICONST_0
    ISTORE 1
   L1
   FRAME APPEND [I]
    ILOAD 1
    ALOAD 0
    INVOKESTATIC java/util/Objects.requireNonNull (Ljava/lang/Object;)Ljava/lang/Object;
    POP
    ICONST_1
    IF_ICMPGE L2
   L3
    LINENUMBER 19 L3
    GETSTATIC java/lang/System.out : Ljava/io/PrintStream;
    LDC "Hello Chasm!"
    INVOKEVIRTUAL java/io/PrintStream.println (Ljava/lang/String;)V
   L4
    LINENUMBER 18 L4
    IINC 1 1
    GOTO L1
   L2
    LINENUMBER 21 L2
   FRAME SAME
    RETURN
   L5
    LOCALVARIABLE this Lother/ExampleClass; L0 L5 0
    LOCALVARIABLE i I L1 L5 1
    MAXSTACK = 2
    MAXLOCALS = 2

  // access flags 0x9
  public static publicStaticMethod()V
    TRYCATCHBLOCK L0 L1 L2 java/lang/Exception
   L3
    LINENUMBER 24 L3
    GETSTATIC java/lang/System.out : Ljava/io/PrintStream;
    LDC "Static Hello Chasm!"
    INVOKEVIRTUAL java/io/PrintStream.println (Ljava/lang/String;)V
   L4
    LINENUMBER 25 L4
    ICONST_5
    ISTORE 0
   L0
    LINENUMBER 27 L0
    GETSTATIC java/lang/System.out : Ljava/io/PrintStream;
    LDC "5 = 5"
    INVOKEVIRTUAL java/io/PrintStream.println (Ljava/lang/String;)V
   L5
    LINENUMBER 28 L5
    ICONST_3
    ISTORE 1
   L6
    LINENUMBER 29 L6
    GETSTATIC java/lang/System.out : Ljava/io/PrintStream;
    ILOAD 0
    ILOAD 1
    ILOAD 0
    ILOAD 1
    IADD
    INVOKEDYNAMIC makeConcatWithConstants(III)Ljava/lang/String; [
      // handle kind 0x6 : INVOKESTATIC
      java/lang/invoke/StringConcatFactory.makeConcatWithConstants(Ljava/lang/invoke/MethodHandles$Lookup;Ljava/lang/String;Ljava/lang/invoke/MethodType;Ljava/lang/String;[Ljava/lang/Object;)Ljava/lang/invoke/CallSite;
      // arguments:
      "\u0001 + \u0001 = \u0001"
    ]
    INVOKEVIRTUAL java/io/PrintStream.println (Ljava/lang/String;)V
   L1
    LINENUMBER 33 L1
    GOTO L7
   L2
    LINENUMBER 30 L2
   FRAME FULL [I] [java/lang/Exception]
    ASTORE 2
   L8
    LINENUMBER 31 L8
    ALOAD 2
    INVOKEVIRTUAL java/lang/Exception.printStackTrace ()V
   L9
    LINENUMBER 32 L9
    ICONST_0
    ISTORE 0
   L7
    LINENUMBER 35 L7
   FRAME SAME
    INVOKESTATIC other/ExampleClass.publicStaticMethod ()V
   L10
    LINENUMBER 37 L10
    ILOAD 0
    LOOKUPSWITCH
      5: L11
      default: L12
   L11
    LINENUMBER 39 L11
   FRAME SAME
    GETSTATIC java/lang/System.out : Ljava/io/PrintStream;
    LDC "Still 5"
    INVOKEVIRTUAL java/io/PrintStream.println (Ljava/lang/String;)V
   L13
    LINENUMBER 40 L13
    GOTO L14
   L12
    LINENUMBER 42 L12
   FRAME SAME
    GETSTATIC java/lang/System.out : Ljava/io/PrintStream;
    LDC "No longer 5"
    INVOKEVIRTUAL java/io/PrintStream.println (Ljava/lang/String;)V
   L14
    LINENUMBER 44 L14
   FRAME SAME
    RETURN
   L15
    LOCALVARIABLE five I L0 L15 0
    LOCALVARIABLE three I L6 L2 1
    LOCALVARIABLE e Ljava/lang/Exception; L8 L7 2
    MAXSTACK = 5
    MAXLOCALS = 3

  // access flags 0x9
  public static testSwitch()Ljava/lang/String;
   L0
    LINENUMBER 47 L0
    INVOKESTATIC java/lang/Math.random ()D
    LDC 100.0
    DMUL
    INVOKESTATIC java/lang/Math.round (D)J
    L2I
    LOOKUPSWITCH
      10: L1
      default: L2
   L1
    LINENUMBER 49 L1
   FRAME SAME
    LDC "Test"
    ASTORE 0
   L3
    LINENUMBER 50 L3
    ALOAD 0
    ASTORE 1
    ICONST_M1
    ISTORE 2
    ALOAD 1
    INVOKEVIRTUAL java/lang/String.hashCode ()I
    LOOKUPSWITCH
      -501589531: L4
      default: L5
   L4
   FRAME APPEND [java/lang/String java/lang/String I]
    ALOAD 1
    LDC "NotTest"
    INVOKEVIRTUAL java/lang/String.equals (Ljava/lang/Object;)Z
    IFEQ L5
    ICONST_0
    ISTORE 2
   L5
   FRAME SAME
    ILOAD 2
    LOOKUPSWITCH
      0: L6
      default: L7
   L6
    LINENUMBER 51 L6
   FRAME SAME
    LDC "NotTest"
    GOTO L8
   L7
    LINENUMBER 52 L7
   FRAME SAME
    NEW java/lang/IllegalStateException
    DUP
    LDC "Unexpected value: Test"
    INVOKESPECIAL java/lang/IllegalStateException.<init> (Ljava/lang/String;)V
    ATHROW
   L8
   FRAME SAME1 java/lang/String
    GOTO L9
   L2
    LINENUMBER 55 L2
   FRAME CHOP 3
    LDC "Not 10"
   L9
    LINENUMBER 47 L9
   FRAME SAME1 java/lang/String
    ARETURN
    LOCALVARIABLE nested Ljava/lang/String; L3 L2 0
    MAXSTACK = 4
    MAXLOCALS = 3

  // access flags 0x9
  public static testGenerics()I throws java/util/concurrent/ExecutionException java/lang/InterruptedException 
   L0
    LINENUMBER 60 L0
    INVOKEDYNAMIC get()Ljava/util/function/Supplier; [
      // handle kind 0x6 : INVOKESTATIC
      java/lang/invoke/LambdaMetafactory.metafactory(Ljava/lang/invoke/MethodHandles$Lookup;Ljava/lang/String;Ljava/lang/invoke/MethodType;Ljava/lang/invoke/MethodType;Ljava/lang/invoke/MethodHandle;Ljava/lang/invoke/MethodType;)Ljava/lang/invoke/CallSite;
      // arguments:
      ()Ljava/lang/Object;, 
      // handle kind 0x6 : INVOKESTATIC
      other/ExampleClass.lambda$testGenerics$0()Ljava/lang/Integer;, 
      ()Ljava/lang/Integer;
    ]
    INVOKESTATIC java/util/concurrent/CompletableFuture.supplyAsync (Ljava/util/function/Supplier;)Ljava/util/concurrent/CompletableFuture;
    INVOKEDYNAMIC apply()Ljava/util/function/Function; [
      // handle kind 0x6 : INVOKESTATIC
      java/lang/invoke/LambdaMetafactory.metafactory(Ljava/lang/invoke/MethodHandles$Lookup;Ljava/lang/String;Ljava/lang/invoke/MethodType;Ljava/lang/invoke/MethodType;Ljava/lang/invoke/MethodHandle;Ljava/lang/invoke/MethodType;)Ljava/lang/invoke/CallSite;
      // arguments:
      (Ljava/lang/Object;)Ljava/lang/Object;, 
      // handle kind 0x6 : INVOKESTATIC
      other/ExampleClass.lambda$testGenerics$1(Ljava/lang/Integer;)Ljava/lang/String;, 
      (Ljava/lang/Integer;)Ljava/lang/String;
    ]
   L1
    LINENUMBER 61 L1
    INVOKEVIRTUAL java/util/concurrent/CompletableFuture.thenApply (Ljava/util/function/Function;)Ljava/util/concurrent/CompletableFuture;
    GETSTATIC java/lang/System.out : Ljava/io/PrintStream;
    DUP
   L2
    LINENUMBER 62 L2
    INVOKESTATIC java/util/Objects.requireNonNull (Ljava/lang/Object;)Ljava/lang/Object;
    POP
    INVOKEDYNAMIC accept(Ljava/io/PrintStream;)Ljava/util/function/Consumer; [
      // handle kind 0x6 : INVOKESTATIC
      java/lang/invoke/LambdaMetafactory.metafactory(Ljava/lang/invoke/MethodHandles$Lookup;Ljava/lang/String;Ljava/lang/invoke/MethodType;Ljava/lang/invoke/MethodType;Ljava/lang/invoke/MethodHandle;Ljava/lang/invoke/MethodType;)Ljava/lang/invoke/CallSite;
      // arguments:
      (Ljava/lang/Object;)V, 
      // handle kind 0x5 : INVOKEVIRTUAL
      java/io/PrintStream.println(Ljava/lang/String;)V, 
      (Ljava/lang/String;)V
    ]
    INVOKEVIRTUAL java/util/concurrent/CompletableFuture.thenAccept (Ljava/util/function/Consumer;)Ljava/util/concurrent/CompletableFuture;
    INVOKEDYNAMIC apply()Ljava/util/function/Function; [
      // handle kind 0x6 : INVOKESTATIC
      java/lang/invoke/LambdaMetafactory.metafactory(Ljava/lang/invoke/MethodHandles$Lookup;Ljava/lang/String;Ljava/lang/invoke/MethodType;Ljava/lang/invoke/MethodType;Ljava/lang/invoke/MethodHandle;Ljava/lang/invoke/MethodType;)Ljava/lang/invoke/CallSite;
      // arguments:
      (Ljava/lang/Object;)Ljava/lang/Object;, 
      // handle kind 0x6 : INVOKESTATIC
      other/ExampleClass.lambda$testGenerics$2(Ljava/lang/Void;)Ljava/lang/Integer;, 
      (Ljava/lang/Void;)Ljava/lang/Integer;
    ]
   L3
    LINENUMBER 63 L3
    INVOKEVIRTUAL java/util/concurrent/CompletableFuture.thenApply (Ljava/util/function/Function;)Ljava/util/concurrent/CompletableFuture;
   L4
    LINENUMBER 64 L4
    INVOKEVIRTUAL java/util/concurrent/CompletableFuture.get ()Ljava/lang/Object;
    CHECKCAST java/lang/Integer
    INVOKEVIRTUAL java/lang/Integer.intValue ()I
    ISTORE 0
   L5
    LINENUMBER 66 L5
    ILOAD 0
    LOOKUPSWITCH
      7: L6
      default: L7
   L6
    LINENUMBER 68 L6
   FRAME APPEND [I]
    BIPUSH 10
    ISTORE 0
   L7
    LINENUMBER 71 L7
   FRAME SAME
    BIPUSH 7
    ISTORE 1
   L8
    LINENUMBER 74 L8
    ILOAD 1
    IRETURN
   L9
    LOCALVARIABLE output I L5 L9 0
    LOCALVARIABLE output I L8 L9 1
    MAXSTACK = 3
    MAXLOCALS = 2

  // access flags 0x401
  public abstract annotationTest(Ljava/lang/String;Ljava/lang/String;)V
    // parameter  <no name>
    // parameter  <no name>
    // annotable parameter count: 2 (invisible)
    @Lother/SimpleAnnotation;(value="first") // invisible, parameter 0
    @Lother/SimpleAnnotation;(value="second") // invisible, parameter 1

  // access flags 0x100A
  private static synthetic lambda$testGenerics$2(Ljava/lang/Void;)Ljava/lang/Integer;
    // parameter  v
   L0
    LINENUMBER 63 L0
    BIPUSH 7
    INVOKESTATIC java/lang/Integer.valueOf (I)Ljava/lang/Integer;
    ARETURN
   L1
    LOCALVARIABLE v Ljava/lang/Void; L0 L1 0
    MAXSTACK = 1
    MAXLOCALS = 1

  // access flags 0x100A
  private static synthetic lambda$testGenerics$1(Ljava/lang/Integer;)Ljava/lang/String;
    // parameter  i
   L0
    LINENUMBER 61 L0
    ALOAD 0
    INVOKEVIRTUAL java/lang/Integer.intValue ()I
    INVOKESTATIC java/lang/Integer.toString (I)Ljava/lang/String;
    ARETURN
   L1
    LOCALVARIABLE i Ljava/lang/Integer; L0 L1 0
    MAXSTACK = 1
    MAXLOCALS = 1

  // access flags 0x100A
  private static synthetic lambda$testGenerics$0()Ljava/lang/Integer;
   L0
    LINENUMBER 60 L0
    ICONST_5
    INVOKESTATIC java/lang/Integer.valueOf (I)Ljava/lang/Integer;
    ARETURN
    MAXSTACK = 1
    MAXLOCALS = 0

  // access flags 0x8
  static <clinit>()V
   L0
    LINENUMBER 14 L0
    LDC 1.2
    PUTSTATIC other/ExampleClass.publicStaticField : D
    RETURN
    MAXSTACK = 2
    MAXLOCALS = 0
}
